{
    "DNDConfig": null,
    "__parentReadjusting__": false,
    "_height_": {
        "type": "string",
        "value": "40dp"
    },
    "_left_": {
        "type": "string",
        "value": "0%"
    },
    "_margin_": [
        0,
        0,
        0,
        0
    ],
    "_orientation_": 6,
    "_padding_": [
        0,
        0,
        0,
        0
    ],
    "_percent_": true,
    "_skin_": "s9b8e70a7ca944f88d37f38b192fa8bb",
    "_top_": {
        "type": "string",
        "value": "0%"
    },
    "_width_": {
        "type": "string",
        "value": "40dp"
    },
    "allboxes": [],
    "autogrowmode": 0,
    "canUpdateUI": true,
    "centery": {
        "type": "string",
        "value": "50%"
    },
    "children": [
        "btnBack"
    ],
    "clipbounds": true,
    "containerweight": 100,
    "enablescrolling": true,
    "focusskin": "s7ed958c89644576a2ecc226c90dd386",
    "id": "flexClickBack",
    "ide_onClick": "AS_FlexContainer_g63b364630f446a392346a5234cd8249",
    "info": null,
    "isvisible": false,
    "kuid": "c76901f3e6004b6b93c953cfd52967e0",
    "layouttype": 2,
    "name": "kony.ui.FlexContainer",
    "parent": "flxHeadingBar",
    "pf": "userwidgetmodel",
    "snapgridsize": 10,
    "snaptogrid": true,
    "wType": "FlexContainer",
    "widgetalignment": 1,
    "zindex": 1
}